{
    "/js/app.js": "/js/app.js",
    "/css/app.css": "/css/app.css",
    "/0.a683ecdbf380a54af4da.hot-update.js": "/0.a683ecdbf380a54af4da.hot-update.js",
    "/0.fc839476a2f4eeac009b.hot-update.js": "/0.fc839476a2f4eeac009b.hot-update.js",
    "/0.15fef12fd405bd502c4a.hot-update.js": "/0.15fef12fd405bd502c4a.hot-update.js",
    "/0.0c5871f7c0bcbbe221a9.hot-update.js": "/0.0c5871f7c0bcbbe221a9.hot-update.js",
    "/0.6570c9f15f0e1299c451.hot-update.js": "/0.6570c9f15f0e1299c451.hot-update.js",
    "/0.093b78aa8e62f61e8890.hot-update.js": "/0.093b78aa8e62f61e8890.hot-update.js",
    "/0.e09927066d63db5363f4.hot-update.js": "/0.e09927066d63db5363f4.hot-update.js",
    "/0.5d9256551efe5d6c69da.hot-update.js": "/0.5d9256551efe5d6c69da.hot-update.js",
    "/0.68dc9dbac12cba37a5bb.hot-update.js": "/0.68dc9dbac12cba37a5bb.hot-update.js",
    "/0.61067acd3e5a97d6ac9c.hot-update.js": "/0.61067acd3e5a97d6ac9c.hot-update.js",
    "/0.6259a4ef1ed307dd1e7e.hot-update.js": "/0.6259a4ef1ed307dd1e7e.hot-update.js",
    "/0.40ac8c7b2d94b927ae3f.hot-update.js": "/0.40ac8c7b2d94b927ae3f.hot-update.js",
    "/0.736ba096206ddb4c6d6d.hot-update.js": "/0.736ba096206ddb4c6d6d.hot-update.js",
    "/0.d5a296f72bcf138cc930.hot-update.js": "/0.d5a296f72bcf138cc930.hot-update.js",
    "/0.d4372a7727758126ee2d.hot-update.js": "/0.d4372a7727758126ee2d.hot-update.js",
    "/0.3dd69f178db0c7da06f7.hot-update.js": "/0.3dd69f178db0c7da06f7.hot-update.js",
    "/0.31ca509d0d5add814bcd.hot-update.js": "/0.31ca509d0d5add814bcd.hot-update.js",
    "/0.18efa613fd0380cb33bf.hot-update.js": "/0.18efa613fd0380cb33bf.hot-update.js",
    "/0.5d439b0f78f6bfd6ff54.hot-update.js": "/0.5d439b0f78f6bfd6ff54.hot-update.js",
    "/0.1f6c171a4d02f77d8da8.hot-update.js": "/0.1f6c171a4d02f77d8da8.hot-update.js",
    "/0.7bf2086e579cf10f5e89.hot-update.js": "/0.7bf2086e579cf10f5e89.hot-update.js",
    "/0.bcf9f442aaf4fe7f34da.hot-update.js": "/0.bcf9f442aaf4fe7f34da.hot-update.js",
    "/0.682004c10baf93010d5e.hot-update.js": "/0.682004c10baf93010d5e.hot-update.js",
    "/0.100dedf521a897358c9e.hot-update.js": "/0.100dedf521a897358c9e.hot-update.js",
    "/0.c60d586504b27d759234.hot-update.js": "/0.c60d586504b27d759234.hot-update.js",
    "/0.06cc9918cd64b02faec5.hot-update.js": "/0.06cc9918cd64b02faec5.hot-update.js",
    "/0.5885028a3df8b18d5a46.hot-update.js": "/0.5885028a3df8b18d5a46.hot-update.js",
    "/0.7704704c184b5ba1393f.hot-update.js": "/0.7704704c184b5ba1393f.hot-update.js",
    "/0.fb26598fb6c079fe57ba.hot-update.js": "/0.fb26598fb6c079fe57ba.hot-update.js",
    "/0.93a65266d08cbb30a46e.hot-update.js": "/0.93a65266d08cbb30a46e.hot-update.js",
    "/0.dd6166fd5e0e832f7eab.hot-update.js": "/0.dd6166fd5e0e832f7eab.hot-update.js",
    "/0.112cfd2d37f97c05d1bb.hot-update.js": "/0.112cfd2d37f97c05d1bb.hot-update.js",
    "/0.782772a65de528745327.hot-update.js": "/0.782772a65de528745327.hot-update.js",
    "/0.aa0909a3f84a776e2eb6.hot-update.js": "/0.aa0909a3f84a776e2eb6.hot-update.js",
    "/0.efb42230db90dd6ea6ad.hot-update.js": "/0.efb42230db90dd6ea6ad.hot-update.js",
    "/0.b74cce0ecf586e221a71.hot-update.js": "/0.b74cce0ecf586e221a71.hot-update.js",
    "/0.d7c47a2281cec3f6ec95.hot-update.js": "/0.d7c47a2281cec3f6ec95.hot-update.js",
    "/0.d5e62a8ad2405848c65d.hot-update.js": "/0.d5e62a8ad2405848c65d.hot-update.js",
    "/0.e03d7abd85f11c4031d6.hot-update.js": "/0.e03d7abd85f11c4031d6.hot-update.js",
    "/0.9ef2ab406a4059a21840.hot-update.js": "/0.9ef2ab406a4059a21840.hot-update.js",
    "/0.537b425d349ee331b125.hot-update.js": "/0.537b425d349ee331b125.hot-update.js",
    "/0.41260820a45daff8873b.hot-update.js": "/0.41260820a45daff8873b.hot-update.js",
    "/0.edfe819a85ef903312c7.hot-update.js": "/0.edfe819a85ef903312c7.hot-update.js",
    "/0.2da9baf2a0ba81c1d66f.hot-update.js": "/0.2da9baf2a0ba81c1d66f.hot-update.js",
    "/0.83703e5980b268e3f873.hot-update.js": "/0.83703e5980b268e3f873.hot-update.js"
}
